dorm/__init__.py
dorm/py.typed
dorm_project-0.2.14.dist-info/METADATA
dorm_project-0.2.14.dist-info/WHEEL
dorm_project-0.2.14.dist-info/entry_points.txt
dorm_project-0.2.14.dist-info/licenses/LICENSE
dorm_project-0.2.14.dist-info/RECORD
