Metadata-Version: 2.4
Name: dorm-project
Version: 0.2.14
Summary: dorm is a minimal Django wrapper that lets you use its ORM independently, without the full framework.
Project-URL: Source code, https://github.com/daadu/dorm
Author-email: Harsh Bhikadia <harsh@bhikadia.com>
License-Expression: MIT
License-File: LICENSE
Keywords: django,django orm,orm
Classifier: Development Status :: 4 - Beta
Classifier: Framework :: Django :: 5
Classifier: Framework :: Django :: 5.0
Classifier: Framework :: Django :: 5.1
Classifier: Intended Audience :: Developers
Classifier: License :: OSI Approved :: MIT License
Classifier: Programming Language :: Python :: 3 :: Only
Classifier: Programming Language :: Python :: 3.10
Classifier: Programming Language :: Python :: 3.11
Classifier: Programming Language :: Python :: 3.12
Classifier: Topic :: Database :: Front-Ends
Requires-Python: >=3.10
Requires-Dist: django<6.0.0,>=5.0.0
